ipysankeywidget/__init__.py
ipysankeywidget/static/widget.css
ipysankeywidget/static/widget.js
ipysankeywidget-0.6.0.dist-info/METADATA
ipysankeywidget-0.6.0.dist-info/WHEEL
ipysankeywidget-0.6.0.dist-info/licenses/LICENCE
ipysankeywidget-0.6.0.dist-info/RECORD
