Metadata-Version: 2.4
Name: ipysankeywidget
Version: 0.6.0
Summary: Display Sankey diagrams in Jupyter
Project-URL: homepage, https://github.com/ricklupton/ipysankeywidget
Author: Rick Lupton
License-Expression: BSD-3-Clause
License-File: LICENCE
Requires-Dist: anywidget
Provides-Extra: dev
Requires-Dist: ipykernel; extra == 'dev'
Requires-Dist: jupyterlab; extra == 'dev'
Requires-Dist: watchfiles; extra == 'dev'
